mdx_poetic.py
mdx_poetic-0.8.dist-info/DESCRIPTION.rst
mdx_poetic-0.8.dist-info/METADATA
mdx_poetic-0.8.dist-info/RECORD
mdx_poetic-0.8.dist-info/WHEEL
mdx_poetic-0.8.dist-info/metadata.json
mdx_poetic-0.8.dist-info/top_level.txt
