Metadata-Version: 2.0
Name: mdx-poetic
Version: 0.8
Summary: Formats poetry in Markdown
Home-page: https://github.com/nickwynja/mdx_poetic
Author: Nick Wynja
License: UNKNOWN
Platform: UNKNOWN
Requires-Dist: markdown (>=2.5)
